Metadata-Version: 1.0
Name: autokaggle
Version: 0.1.0
Summary: AutoML for Kaggle Competitions
Home-page: UNKNOWN
Author: DATA Lab at Texas A&M University
Author-email: jhfjhfj1@gmail.com
License: UNKNOWN
Keywords: AutoML,Kaggle
Platform: UNKNOWN
